CssQuanweiZhinan4thFix1/README.md
CssQuanweiZhinan4thFix1/__init__.py
CssQuanweiZhinan4thFix1/__main__.py
CssQuanweiZhinan4thFix1/file.epub
CssQuanweiZhinan4thFix1/index.html
CssQuanweiZhinan4thFix1/css/__init__.py
CssQuanweiZhinan4thFix1/css/annotations.css
CssQuanweiZhinan4thFix1/css/main.css
CssQuanweiZhinan4thFix1/css/normalize.css
CssQuanweiZhinan4thFix1/css/popup.css
CssQuanweiZhinan4thFix1/font/__init__.py
CssQuanweiZhinan4thFix1/font/fontello.eot
CssQuanweiZhinan4thFix1/font/fontello.svg
CssQuanweiZhinan4thFix1/font/fontello.ttf
CssQuanweiZhinan4thFix1/font/fontello.woff
CssQuanweiZhinan4thFix1/img/__init__.py
CssQuanweiZhinan4thFix1/img/annotator-glyph-sprite.png
CssQuanweiZhinan4thFix1/img/annotator-icon-sprite.png
CssQuanweiZhinan4thFix1/img/apple-touch-icon.png
CssQuanweiZhinan4thFix1/img/cancelfullscreen.png
CssQuanweiZhinan4thFix1/img/close.png
CssQuanweiZhinan4thFix1/img/fullscreen.png
CssQuanweiZhinan4thFix1/img/loader.gif
CssQuanweiZhinan4thFix1/img/menu-icon.png
CssQuanweiZhinan4thFix1/img/save.png
CssQuanweiZhinan4thFix1/img/saved.png
CssQuanweiZhinan4thFix1/img/settings-s.png
CssQuanweiZhinan4thFix1/img/settings.png
CssQuanweiZhinan4thFix1/img/star.png
CssQuanweiZhinan4thFix1/js/__init__.py
CssQuanweiZhinan4thFix1/js/epub.js
CssQuanweiZhinan4thFix1/js/epub.min.js
CssQuanweiZhinan4thFix1/js/epub.min.map
CssQuanweiZhinan4thFix1/js/hooks.min.js
CssQuanweiZhinan4thFix1/js/hooks.min.map
CssQuanweiZhinan4thFix1/js/reader.js
CssQuanweiZhinan4thFix1/js/reader.js.map
CssQuanweiZhinan4thFix1/js/reader.min.js
CssQuanweiZhinan4thFix1/js/reader.min.map
CssQuanweiZhinan4thFix1/js/hooks/__init__.py
CssQuanweiZhinan4thFix1/js/hooks/extensions/__init__.py
CssQuanweiZhinan4thFix1/js/hooks/extensions/highlight.js
CssQuanweiZhinan4thFix1/js/libs/__init__.py
CssQuanweiZhinan4thFix1/js/libs/jquery.min.js
CssQuanweiZhinan4thFix1/js/libs/localforage.min.js
CssQuanweiZhinan4thFix1/js/libs/screenfull.js
CssQuanweiZhinan4thFix1/js/libs/screenfull.min.js
css_quanwei_zhinan_4th_fix1-2025.3.24.2.dist-info/METADATA
css_quanwei_zhinan_4th_fix1-2025.3.24.2.dist-info/WHEEL
css_quanwei_zhinan_4th_fix1-2025.3.24.2.dist-info/entry_points.txt
css_quanwei_zhinan_4th_fix1-2025.3.24.2.dist-info/top_level.txt
css_quanwei_zhinan_4th_fix1-2025.3.24.2.dist-info/RECORD
